{
  "before": {
    "cameraCanvas": {
      "bottom": 210.8000030517578,
      "height": 132,
      "left": 439.6000061035156,
      "right": 571.6000061035156,
      "top": 78.80000305175781,
      "width": 132
    },
    "canvasRects": [
      {
        "bottom": 697.5999870300293,
        "height": 640.7999877929688,
        "left": 0,
        "right": 593.6000366210938,
        "top": 56.79999923706055,
        "width": 593.6000366210938
      },
      {
        "bottom": 210.8000030517578,
        "height": 132,
        "left": 439.6000061035156,
        "right": 571.6000061035156,
        "top": 78.80000305175781,
        "width": 132
      }
    ],
    "floatingWindows": [
      {
        "className": "floating-gizmo-window debug-log-window",
        "frameClose": {
          "bottom": 470.3999938964844,
          "height": 22,
          "left": 549.7999877929688,
          "right": 571.7999877929688,
          "top": 448.3999938964844,
          "width": 22
        },
        "hidden": false,
        "rect": {
          "bottom": 684,
          "height": 240,
          "left": 14,
          "right": 579.6000366210938,
          "top": 444,
          "width": 565.6000366210938
        },
        "tabs": [
          {
            "className": "window-frame-tab floating-gizmo-window__title floating-gizmo-window__tab is-active",
            "close": {
              "bottom": 467.3999938964844,
              "height": 16,
              "left": 153,
              "right": 169,
              "top": 451.3999938964844,
              "width": 16
            },
            "rect": {
              "bottom": 471.3999938964844,
              "height": 24,
              "left": 24.80000114440918,
              "right": 174.80000114440918,
              "top": 447.3999938964844,
              "width": 150
            },
            "text": "Debug Logx"
          }
        ]
      },
      {
        "className": "floating-gizmo-window hierarchy-window",
        "frameClose": {
          "bottom": 40.39999961853027,
          "height": 22,
          "left": 264.20001220703125,
          "right": 286.20001220703125,
          "top": 18.399999618530273,
          "width": 22
        },
        "hidden": false,
        "rect": {
          "bottom": 374,
          "height": 360,
          "left": 14,
          "right": 294,
          "top": 14,
          "width": 280
        },
        "tabs": [
          {
            "className": "window-frame-tab floating-gizmo-window__title floating-gizmo-window__tab is-active",
            "close": {
              "bottom": 37.39999961853027,
              "height": 16,
              "left": 153,
              "right": 169,
              "top": 21.399999618530273,
              "width": 16
            },
            "rect": {
              "bottom": 41.39999961853027,
              "height": 24,
              "left": 24.80000114440918,
              "right": 174.80000114440918,
              "top": 17.399999618530273,
              "width": 150
            },
            "text": "Hierarchyx"
          }
        ]
      }
    ],
    "menuRows": [
      {
        "hidden": false,
        "rect": {
          "bottom": 0,
          "height": 0,
          "left": 0,
          "right": 0,
          "top": 0,
          "width": 0
        },
        "text": "Scene"
      },
      {
        "hidden": false,
        "rect": {
          "bottom": 0,
          "height": 0,
          "left": 0,
          "right": 0,
          "top": 0,
          "width": 0
        },
        "text": "Debug Log Window"
      },
      {
        "hidden": false,
        "rect": {
          "bottom": 0,
          "height": 0,
          "left": 0,
          "right": 0,
          "top": 0,
          "width": 0
        },
        "text": "Hierarchy Panel"
      }
    ],
    "rootTabs": [
      {
        "className": "window-frame-tab workspace-root-dock-frame__tab is-active",
        "close": {
          "bottom": 50,
          "height": 16,
          "left": 134.1999969482422,
          "right": 150.1999969482422,
          "top": 34,
          "width": 16
        },
        "rect": {
          "bottom": 54,
          "height": 24,
          "left": 6,
          "right": 156,
          "top": 30,
          "width": 150
        },
        "text": "Scenex"
      }
    ],
    "viewport": {
      "height": 698,
      "width": 594
    },
    "windowButton": {
      "bottom": 36,
      "height": 26,
      "left": 513.6000366210938,
      "right": 581.6000366210938,
      "top": 10,
      "width": 68
    }
  },
  "afterDrag": {
    "cameraCanvas": {
      "bottom": 210.8000030517578,
      "height": 132,
      "left": 439.6000061035156,
      "right": 571.6000061035156,
      "top": 78.80000305175781,
      "width": 132
    },
    "canvasRects": [
      {
        "bottom": 697.5999870300293,
        "height": 640.7999877929688,
        "left": 0,
        "right": 593.6000366210938,
        "top": 56.79999923706055,
        "width": 593.6000366210938
      },
      {
        "bottom": 210.8000030517578,
        "height": 132,
        "left": 439.6000061035156,
        "right": 571.6000061035156,
        "top": 78.80000305175781,
        "width": 132
      }
    ],
    "floatingWindows": [
      {
        "className": "floating-gizmo-window debug-log-window",
        "frameClose": {
          "bottom": 470.3999938964844,
          "height": 22,
          "left": 549.7999877929688,
          "right": 571.7999877929688,
          "top": 448.3999938964844,
          "width": 22
        },
        "hidden": false,
        "rect": {
          "bottom": 684,
          "height": 240,
          "left": 14,
          "right": 579.6000366210938,
          "top": 444,
          "width": 565.6000366210938
        },
        "tabs": [
          {
            "className": "window-frame-tab floating-gizmo-window__title floating-gizmo-window__tab is-active",
            "close": {
              "bottom": 467.3999938964844,
              "height": 16,
              "left": 153,
              "right": 169,
              "top": 451.3999938964844,
              "width": 16
            },
            "rect": {
              "bottom": 471.3999938964844,
              "height": 24,
              "left": 24.80000114440918,
              "right": 174.80000114440918,
              "top": 447.3999938964844,
              "width": 150
            },
            "text": "Debug Logx"
          }
        ]
      },
      {
        "className": "floating-gizmo-window hierarchy-window",
        "frameClose": {
          "bottom": 100.4000015258789,
          "height": 22,
          "left": 384.20001220703125,
          "right": 406.20001220703125,
          "top": 78.4000015258789,
          "width": 22
        },
        "hidden": false,
        "rect": {
          "bottom": 434,
          "height": 360,
          "left": 134,
          "right": 414,
          "top": 74,
          "width": 280
        },
        "tabs": [
          {
            "className": "window-frame-tab floating-gizmo-window__title floating-gizmo-window__tab is-active",
            "close": {
              "bottom": 97.4000015258789,
              "height": 16,
              "left": 273,
              "right": 289,
              "top": 81.4000015258789,
              "width": 16
            },
            "rect": {
              "bottom": 101.4000015258789,
              "height": 24,
              "left": 144.8000030517578,
              "right": 294.8000030517578,
              "top": 77.4000015258789,
              "width": 150
            },
            "text": "Hierarchyx"
          }
        ]
      }
    ],
    "menuRows": [
      {
        "hidden": false,
        "rect": {
          "bottom": 0,
          "height": 0,
          "left": 0,
          "right": 0,
          "top": 0,
          "width": 0
        },
        "text": "Scene"
      },
      {
        "hidden": false,
        "rect": {
          "bottom": 0,
          "height": 0,
          "left": 0,
          "right": 0,
          "top": 0,
          "width": 0
        },
        "text": "Debug Log Window"
      },
      {
        "hidden": false,
        "rect": {
          "bottom": 0,
          "height": 0,
          "left": 0,
          "right": 0,
          "top": 0,
          "width": 0
        },
        "text": "Hierarchy Panel"
      }
    ],
    "rootTabs": [
      {
        "className": "window-frame-tab workspace-root-dock-frame__tab is-active",
        "close": {
          "bottom": 50,
          "height": 16,
          "left": 134.1999969482422,
          "right": 150.1999969482422,
          "top": 34,
          "width": 16
        },
        "rect": {
          "bottom": 54,
          "height": 24,
          "left": 6,
          "right": 156,
          "top": 30,
          "width": 150
        },
        "text": "Scenex"
      }
    ],
    "viewport": {
      "height": 698,
      "width": 594
    },
    "windowButton": {
      "bottom": 36,
      "height": 26,
      "left": 513.6000366210938,
      "right": 581.6000366210938,
      "top": 10,
      "width": 68
    }
  },
  "afterCameraDrag": {
    "cameraCanvas": {
      "bottom": 210.8000030517578,
      "height": 132,
      "left": 439.6000061035156,
      "right": 571.6000061035156,
      "top": 78.80000305175781,
      "width": 132
    },
    "canvasRects": [
      {
        "bottom": 697.5999870300293,
        "height": 640.7999877929688,
        "left": 0,
        "right": 593.6000366210938,
        "top": 56.79999923706055,
        "width": 593.6000366210938
      },
      {
        "bottom": 210.8000030517578,
        "height": 132,
        "left": 439.6000061035156,
        "right": 571.6000061035156,
        "top": 78.80000305175781,
        "width": 132
      }
    ],
    "floatingWindows": [
      {
        "className": "floating-gizmo-window debug-log-window",
        "frameClose": {
          "bottom": 470.3999938964844,
          "height": 22,
          "left": 549.7999877929688,
          "right": 571.7999877929688,
          "top": 448.3999938964844,
          "width": 22
        },
        "hidden": false,
        "rect": {
          "bottom": 684,
          "height": 240,
          "left": 14,
          "right": 579.6000366210938,
          "top": 444,
          "width": 565.6000366210938
        },
        "tabs": [
          {
            "className": "window-frame-tab floating-gizmo-window__title floating-gizmo-window__tab is-active",
            "close": {
              "bottom": 467.3999938964844,
              "height": 16,
              "left": 153,
              "right": 169,
              "top": 451.3999938964844,
              "width": 16
            },
            "rect": {
              "bottom": 471.3999938964844,
              "height": 24,
              "left": 24.80000114440918,
              "right": 174.80000114440918,
              "top": 447.3999938964844,
              "width": 150
            },
            "text": "Debug Logx"
          }
        ]
      },
      {
        "className": "floating-gizmo-window hierarchy-window",
        "frameClose": {
          "bottom": 100.4000015258789,
          "height": 22,
          "left": 384.20001220703125,
          "right": 406.20001220703125,
          "top": 78.4000015258789,
          "width": 22
        },
        "hidden": false,
        "rect": {
          "bottom": 434,
          "height": 360,
          "left": 134,
          "right": 414,
          "top": 74,
          "width": 280
        },
        "tabs": [
          {
            "className": "window-frame-tab floating-gizmo-window__title floating-gizmo-window__tab is-active",
            "close": {
              "bottom": 97.4000015258789,
              "height": 16,
              "left": 273,
              "right": 289,
              "top": 81.4000015258789,
              "width": 16
            },
            "rect": {
              "bottom": 101.4000015258789,
              "height": 24,
              "left": 144.8000030517578,
              "right": 294.8000030517578,
              "top": 77.4000015258789,
              "width": 150
            },
            "text": "Hierarchyx"
          }
        ]
      }
    ],
    "menuRows": [
      {
        "hidden": false,
        "rect": {
          "bottom": 0,
          "height": 0,
          "left": 0,
          "right": 0,
          "top": 0,
          "width": 0
        },
        "text": "Scene"
      },
      {
        "hidden": false,
        "rect": {
          "bottom": 0,
          "height": 0,
          "left": 0,
          "right": 0,
          "top": 0,
          "width": 0
        },
        "text": "Debug Log Window"
      },
      {
        "hidden": false,
        "rect": {
          "bottom": 0,
          "height": 0,
          "left": 0,
          "right": 0,
          "top": 0,
          "width": 0
        },
        "text": "Hierarchy Panel"
      }
    ],
    "rootTabs": [
      {
        "className": "window-frame-tab workspace-root-dock-frame__tab is-active",
        "close": {
          "bottom": 50,
          "height": 16,
          "left": 134.1999969482422,
          "right": 150.1999969482422,
          "top": 34,
          "width": 16
        },
        "rect": {
          "bottom": 54,
          "height": 24,
          "left": 6,
          "right": 156,
          "top": 30,
          "width": 150
        },
        "text": "Scenex"
      }
    ],
    "viewport": {
      "height": 698,
      "width": 594
    },
    "windowButton": {
      "bottom": 36,
      "height": 26,
      "left": 513.6000366210938,
      "right": 581.6000366210938,
      "top": 10,
      "width": 68
    }
  },
  "menuOpen": {
    "cameraCanvas": {
      "bottom": 210.8000030517578,
      "height": 132,
      "left": 439.6000061035156,
      "right": 571.6000061035156,
      "top": 78.80000305175781,
      "width": 132
    },
    "canvasRects": [
      {
        "bottom": 697.5999870300293,
        "height": 640.7999877929688,
        "left": 0,
        "right": 593.6000366210938,
        "top": 56.79999923706055,
        "width": 593.6000366210938
      },
      {
        "bottom": 210.8000030517578,
        "height": 132,
        "left": 439.6000061035156,
        "right": 571.6000061035156,
        "top": 78.80000305175781,
        "width": 132
      }
    ],
    "floatingWindows": [
      {
        "className": "floating-gizmo-window debug-log-window",
        "frameClose": {
          "bottom": 470.3999938964844,
          "height": 22,
          "left": 549.7999877929688,
          "right": 571.7999877929688,
          "top": 448.3999938964844,
          "width": 22
        },
        "hidden": false,
        "rect": {
          "bottom": 684,
          "height": 240,
          "left": 14,
          "right": 579.6000366210938,
          "top": 444,
          "width": 565.6000366210938
        },
        "tabs": [
          {
            "className": "window-frame-tab floating-gizmo-window__title floating-gizmo-window__tab is-active",
            "close": {
              "bottom": 467.3999938964844,
              "height": 16,
              "left": 153,
              "right": 169,
              "top": 451.3999938964844,
              "width": 16
            },
            "rect": {
              "bottom": 471.3999938964844,
              "height": 24,
              "left": 24.80000114440918,
              "right": 174.80000114440918,
              "top": 447.3999938964844,
              "width": 150
            },
            "text": "Debug Logx"
          }
        ]
      },
      {
        "className": "floating-gizmo-window hierarchy-window",
        "frameClose": {
          "bottom": 100.4000015258789,
          "height": 22,
          "left": 384.20001220703125,
          "right": 406.20001220703125,
          "top": 78.4000015258789,
          "width": 22
        },
        "hidden": false,
        "rect": {
          "bottom": 434,
          "height": 360,
          "left": 134,
          "right": 414,
          "top": 74,
          "width": 280
        },
        "tabs": [
          {
            "className": "window-frame-tab floating-gizmo-window__title floating-gizmo-window__tab is-active",
            "close": {
              "bottom": 97.4000015258789,
              "height": 16,
              "left": 273,
              "right": 289,
              "top": 81.4000015258789,
              "width": 16
            },
            "rect": {
              "bottom": 101.4000015258789,
              "height": 24,
              "left": 144.8000030517578,
              "right": 294.8000030517578,
              "top": 77.4000015258789,
              "width": 150
            },
            "text": "Hierarchyx"
          }
        ]
      }
    ],
    "menuRows": [
      {
        "hidden": false,
        "rect": {
          "bottom": 69.79999923706055,
          "height": 24,
          "left": 418.3999938964844,
          "right": 576.8000030517578,
          "top": 45.79999923706055,
          "width": 158.40000915527344
        },
        "text": "Scene"
      },
      {
        "hidden": false,
        "rect": {
          "bottom": 93.80000305175781,
          "height": 24,
          "left": 418.3999938964844,
          "right": 576.8000030517578,
          "top": 69.80000305175781,
          "width": 158.40000915527344
        },
        "text": "Debug Log Window"
      },
      {
        "hidden": false,
        "rect": {
          "bottom": 117.80000305175781,
          "height": 24,
          "left": 418.3999938964844,
          "right": 576.8000030517578,
          "top": 93.80000305175781,
          "width": 158.40000915527344
        },
        "text": "Hierarchy Panel"
      }
    ],
    "rootTabs": [
      {
        "className": "window-frame-tab workspace-root-dock-frame__tab is-active",
        "close": {
          "bottom": 50,
          "height": 16,
          "left": 134.1999969482422,
          "right": 150.1999969482422,
          "top": 34,
          "width": 16
        },
        "rect": {
          "bottom": 54,
          "height": 24,
          "left": 6,
          "right": 156,
          "top": 30,
          "width": 150
        },
        "text": "Scenex"
      }
    ],
    "viewport": {
      "height": 698,
      "width": 594
    },
    "windowButton": {
      "bottom": 36,
      "height": 26,
      "left": 513.6000366210938,
      "right": 581.6000366210938,
      "top": 10,
      "width": 68
    }
  },
  "afterMenu": {
    "cameraCanvas": {
      "bottom": 210.8000030517578,
      "height": 132,
      "left": 439.6000061035156,
      "right": 571.6000061035156,
      "top": 78.80000305175781,
      "width": 132
    },
    "canvasRects": [
      {
        "bottom": 697.5999870300293,
        "height": 640.7999877929688,
        "left": 0,
        "right": 593.6000366210938,
        "top": 56.79999923706055,
        "width": 593.6000366210938
      },
      {
        "bottom": 210.8000030517578,
        "height": 132,
        "left": 439.6000061035156,
        "right": 571.6000061035156,
        "top": 78.80000305175781,
        "width": 132
      }
    ],
    "floatingWindows": [
      {
        "className": "floating-gizmo-window debug-log-window",
        "frameClose": {
          "bottom": 470.3999938964844,
          "height": 22,
          "left": 549.7999877929688,
          "right": 571.7999877929688,
          "top": 448.3999938964844,
          "width": 22
        },
        "hidden": false,
        "rect": {
          "bottom": 684,
          "height": 240,
          "left": 14,
          "right": 579.6000366210938,
          "top": 444,
          "width": 565.6000366210938
        },
        "tabs": [
          {
            "className": "window-frame-tab floating-gizmo-window__title floating-gizmo-window__tab is-active",
            "close": {
              "bottom": 467.3999938964844,
              "height": 16,
              "left": 153,
              "right": 169,
              "top": 451.3999938964844,
              "width": 16
            },
            "rect": {
              "bottom": 471.3999938964844,
              "height": 24,
              "left": 24.80000114440918,
              "right": 174.80000114440918,
              "top": 447.3999938964844,
              "width": 150
            },
            "text": "Debug Logx"
          }
        ]
      },
      {
        "className": "floating-gizmo-window hierarchy-window",
        "frameClose": {
          "bottom": 100.4000015258789,
          "height": 22,
          "left": 384.20001220703125,
          "right": 406.20001220703125,
          "top": 78.4000015258789,
          "width": 22
        },
        "hidden": false,
        "rect": {
          "bottom": 434,
          "height": 360,
          "left": 134,
          "right": 414,
          "top": 74,
          "width": 280
        },
        "tabs": [
          {
            "className": "window-frame-tab floating-gizmo-window__title floating-gizmo-window__tab is-active",
            "close": {
              "bottom": 97.4000015258789,
              "height": 16,
              "left": 273,
              "right": 289,
              "top": 81.4000015258789,
              "width": 16
            },
            "rect": {
              "bottom": 101.4000015258789,
              "height": 24,
              "left": 144.8000030517578,
              "right": 294.8000030517578,
              "top": 77.4000015258789,
              "width": 150
            },
            "text": "Hierarchyx"
          }
        ]
      }
    ],
    "menuRows": [
      {
        "hidden": false,
        "rect": {
          "bottom": 0,
          "height": 0,
          "left": 0,
          "right": 0,
          "top": 0,
          "width": 0
        },
        "text": "Scene"
      },
      {
        "hidden": false,
        "rect": {
          "bottom": 0,
          "height": 0,
          "left": 0,
          "right": 0,
          "top": 0,
          "width": 0
        },
        "text": "Debug Log Window"
      },
      {
        "hidden": false,
        "rect": {
          "bottom": 0,
          "height": 0,
          "left": 0,
          "right": 0,
          "top": 0,
          "width": 0
        },
        "text": "Hierarchy Panel"
      }
    ],
    "rootTabs": [
      {
        "className": "window-frame-tab workspace-root-dock-frame__tab is-active",
        "close": {
          "bottom": 50,
          "height": 16,
          "left": 134.1999969482422,
          "right": 150.1999969482422,
          "top": 34,
          "width": 16
        },
        "rect": {
          "bottom": 54,
          "height": 24,
          "left": 6,
          "right": 156,
          "top": 30,
          "width": 150
        },
        "text": "Scenex"
      }
    ],
    "viewport": {
      "height": 698,
      "width": 594
    },
    "windowButton": {
      "bottom": 36,
      "height": 26,
      "left": 513.6000366210938,
      "right": 581.6000366210938,
      "top": 10,
      "width": 68
    }
  },
  "logs": []
}